truthtable/__init__.py
truthtable/helptext.py
truthtable/logicaloperators.py
truthtable/operators.py
truthtable/symbols.py
truthtable/table.py
truthtable-0.0.1.data/scripts/Truthtable
truthtable-0.0.1.dist-info/METADATA
truthtable-0.0.1.dist-info/RECORD
truthtable-0.0.1.dist-info/WHEEL
truthtable-0.0.1.dist-info/top_level.txt
