Metadata-Version: 2.1
Name: truthtable
Version: 0.0.1
Summary: Small program to build truth tables from expressions
Home-page: https://github.com/Iheiko/truthtable/
Author: Viktor Prymak
Author-email: sammorow@gmail.com
License: UNKNOWN
Platform: UNKNOWN
Classifier: Programming Language :: Python :: 3
Classifier: Topic :: Education
Classifier: Environment :: Console
Classifier: License :: OSI Approved :: MIT License
Classifier: Operating System :: OS Independent
Requires-Dist: prettytable
